{"212777492833@s.whatsapp.net":true,"218913829711@s.whatsapp.net":true,"201065105523@s.whatsapp.net":true,"201286954690@s.whatsapp.net":true,"201001355187@s.whatsapp.net":true,"201002163636@s.whatsapp.net":true,"201224362978@s.whatsapp.net":true,"201018171720@s.whatsapp.net":true,"201027519858@s.whatsapp.net":true,"201140724742@s.whatsapp.net":true,"201003187043@s.whatsapp.net":true,"218918137277@s.whatsapp.net":true,"218918137277:2@s.whatsapp.net":true,"201126406450@s.whatsapp.net":true,"201154185847@s.whatsapp.net":true,"201140747574@s.whatsapp.net":true,"201212263154@s.whatsapp.net":true,"201021006612@s.whatsapp.net":true,"971556119704@s.whatsapp.net":true,"971556119704:15@s.whatsapp.net":true,"971556119704:16@s.whatsapp.net":true,"201033051718@s.whatsapp.net":true,"212709962819@s.whatsapp.net":true,"201559633308@s.whatsapp.net":true,"201157425035@s.whatsapp.net":true,"201094253149@s.whatsapp.net":true,"249128199586@s.whatsapp.net":true,"201117432833@s.whatsapp.net":true,"201061386364@s.whatsapp.net":true,"212703777473@s.whatsapp.net":true,"201029640341@s.whatsapp.net":true,"201064272589@s.whatsapp.net":true,"996222032649@s.whatsapp.net":true,"218919265406@s.whatsapp.net":true,"201111139267@s.whatsapp.net":true,"201011003582@s.whatsapp.net":true,"967714841049@s.whatsapp.net":true,"201024568974@s.whatsapp.net":true,"201551714560@s.whatsapp.net":true,"967780099486@s.whatsapp.net":true,"962790478051@s.whatsapp.net":true,"218914062522@s.whatsapp.net":true,"967776235556@s.whatsapp.net":true,"212771950043@s.whatsapp.net":true,"212771950043:2@s.whatsapp.net":true,"212771950043:4@s.whatsapp.net":true,"212771950043:9@s.whatsapp.net":true,"963935165258@s.whatsapp.net":true,"201060476604@s.whatsapp.net":true,"201027132424@s.whatsapp.net":true,"201555034316@s.whatsapp.net":true,"201224817673@s.whatsapp.net":true,"249912632695@s.whatsapp.net":true,"66617859263@s.whatsapp.net":true,"967733260790@s.whatsapp.net":true,"201112372376@s.whatsapp.net":true,"218917903385@s.whatsapp.net":true,"967776615644@s.whatsapp.net":true,"218927287510@s.whatsapp.net":true,"966510905958@s.whatsapp.net":true,"962778034813@s.whatsapp.net":true,"9647742206559@s.whatsapp.net":true,"213551894083@s.whatsapp.net":true,"201061568714@s.whatsapp.net":true,"967734858046@s.whatsapp.net":true,"201112430217@s.whatsapp.net":true,"249129383702@s.whatsapp.net":true,"9647730164339@s.whatsapp.net":true,"201270012740@s.whatsapp.net":true,"249115960838@s.whatsapp.net":true,"201064009494@s.whatsapp.net":true,"201090877334@s.whatsapp.net":true,"201030602157@s.whatsapp.net":true,"963953365082@s.whatsapp.net":true,"201016390571@s.whatsapp.net":true,"967772887075@s.whatsapp.net":true,"201096112473@s.whatsapp.net":true,"218918976838@s.whatsapp.net":true,"972525335471@s.whatsapp.net":true,"201002302462@s.whatsapp.net":true,"201116899044@s.whatsapp.net":true,"201280343874@s.whatsapp.net":true,"966501030542@s.whatsapp.net":true,"212657424658@s.whatsapp.net":true,"201212443997@s.whatsapp.net":true,"212693889527@s.whatsapp.net":true,"967730416331@s.whatsapp.net":true,"201289488359@s.whatsapp.net":true,"963952335639@s.whatsapp.net":true,"201204879364@s.whatsapp.net":true,"201140821903@s.whatsapp.net":true,"963935126299@s.whatsapp.net":true,"17205999683@s.whatsapp.net":true,"201558525154@s.whatsapp.net":true,"218917809014@s.whatsapp.net":true,"249960595625@s.whatsapp.net":true,"249920566797@s.whatsapp.net":true,"967780137438@s.whatsapp.net":true,"201017011519@s.whatsapp.net":true,"201201152578@s.whatsapp.net":true,"14073924780@s.whatsapp.net":true,"9647740511123@s.whatsapp.net":true,"967734951622@s.whatsapp.net":true,"967737912578@s.whatsapp.net":true,"963964768480@s.whatsapp.net":true,"201095275969@s.whatsapp.net":true,"218922497463@s.whatsapp.net":true,"9613684723@s.whatsapp.net":true,"201144647463@s.whatsapp.net":true,"201006020425@s.whatsapp.net":true,"201098758493@s.whatsapp.net":true,"971556119704:17@s.whatsapp.net":true}